pytarkov/__init__.py
pytarkov/pytarkov.py
pytarkov-1.1.0.dist-info/LICENSE
pytarkov-1.1.0.dist-info/METADATA
pytarkov-1.1.0.dist-info/WHEEL
pytarkov-1.1.0.dist-info/top_level.txt
pytarkov-1.1.0.dist-info/RECORD
