Metadata-Version: 2.1
Name: pytarkov
Version: 1.1.0
Summary: An API wrapper for Tarkov-Market written in Python.
Home-page: https://github.com/matix2/pytarkov
Author: matix
Author-email: matixidk@gmail.com
License: UNKNOWN
Project-URL: Bug Tracker, https://github.com/matix2/pytarkov/issues
Platform: UNKNOWN
Classifier: Programming Language :: Python :: 3
Classifier: License :: OSI Approved :: MIT License
Classifier: Operating System :: OS Independent
Requires-Python: >=3.6
